[
  {
    "full_name": "siglens/siglens",
    "stargazers_count": 1087,
    "open_issues_count": 142,
    "forks_count": 161
  },
  {
    "full_name": "LukeMathWalker/pavex",
    "stargazers_count": 1604,
    "open_issues_count": 7,
    "forks_count": 54
  },
  {
    "full_name": "plume-lang/plume",
    "stargazers_count": 7,
    "open_issues_count": 7,
    "forks_count": 2
  },
  {
    "full_name": "Delioos/crypto-curious-crusaders",
    "stargazers_count": 1,
    "open_issues_count": 0,
    "forks_count": 0
  },
  {
    "full_name": "gitbutlerapp/gitbutler",
    "stargazers_count": 10974,
    "open_issues_count": 222,
    "forks_count": 451
  },
  {
    "full_name": "lukeed/clsx",
    "stargazers_count": 7554,
    "open_issues_count": 9,
    "forks_count": 135
  },
  {
    "full_name": "zed-industries/zed",
    "stargazers_count": 35007,
    "open_issues_count": 2041,
    "forks_count": 1758
  },
  {
    "full_name": "dotnet/reactive",
    "stargazers_count": 6534,
    "open_issues_count": 159,
    "forks_count": 734
  },
  {
    "full_name": "floriankyn/MindToy-Discord-Bot",
    "stargazers_count": 6,
    "open_issues_count": 0,
    "forks_count": 1
  },
  {
    "full_name": "microsoft/reverse-proxy",
    "stargazers_count": 8159,
    "open_issues_count": 153,
    "forks_count": 803
  },
  {
    "full_name": "asc-lab/dotnetcore-microservices-poc",
    "stargazers_count": 1861,
    "open_issues_count": 6,
    "forks_count": 677
  },
  {
    "full_name": "charmbracelet/bubbletea",
    "stargazers_count": 24722,
    "open_issues_count": 97,
    "forks_count": 717
  },
  {
    "full_name": "expo/expo",
    "stargazers_count": 29915,
    "open_issues_count": 667,
    "forks_count": 4711
  },
  {
    "full_name": "sst/sst",
    "stargazers_count": 20505,
    "open_issues_count": 807,
    "forks_count": 1602
  },
  {
    "full_name": "joeferner/redis-commander",
    "stargazers_count": 3526,
    "open_issues_count": 54,
    "forks_count": 456
  },
  {
    "full_name": "nuxt/nuxt",
    "stargazers_count": 52445,
    "open_issues_count": 1037,
    "forks_count": 4795
  },
  {
    "full_name": "abi/screenshot-to-code",
    "stargazers_count": 52422,
    "open_issues_count": 52,
    "forks_count": 6342
  },
  {
    "full_name": "biomejs/biome",
    "stargazers_count": 11200,
    "open_issues_count": 161,
    "forks_count": 369
  },
  {
    "full_name": "dotnet/aspire-samples",
    "stargazers_count": 468,
    "open_issues_count": 77,
    "forks_count": 122
  },
  {
    "full_name": "dotnet/aspire",
    "stargazers_count": 3135,
    "open_issues_count": 636,
    "forks_count": 298
  },
  {
    "full_name": "dragonflydb/dragonfly",
    "stargazers_count": 24119,
    "open_issues_count": 152,
    "forks_count": 869
  },
  {
    "full_name": "analogjs/analog",
    "stargazers_count": 2322,
    "open_issues_count": 47,
    "forks_count": 210
  },
  {
    "full_name": "JasperFx/wolverine",
    "stargazers_count": 1146,
    "open_issues_count": 66,
    "forks_count": 121
  },
  {
    "full_name": "oskardudycz/EventSourcing.NetCore",
    "stargazers_count": 3284,
    "open_issues_count": 20,
    "forks_count": 502
  },
  {
    "full_name": "angular/angular",
    "stargazers_count": 94850,
    "open_issues_count": 1556,
    "forks_count": 24732
  },
  {
    "full_name": "nicolargo/glances",
    "stargazers_count": 25284,
    "open_issues_count": 224,
    "forks_count": 1449
  },
  {
    "full_name": "quarkusio/quarkus",
    "stargazers_count": 13212,
    "open_issues_count": 2614,
    "forks_count": 2521
  },
  {
    "full_name": "react-hook-form/react-hook-form",
    "stargazers_count": 39946,
    "open_issues_count": 35,
    "forks_count": 1993
  },
  {
    "full_name": "t3dotgg/server-actions-trpc-examples",
    "stargazers_count": 109,
    "open_issues_count": 2,
    "forks_count": 14
  },
  {
    "full_name": "openstatusHQ/openstatus",
    "stargazers_count": 4501,
    "open_issues_count": 62,
    "forks_count": 251
  }
]