[
  {
    "full_name": "sisypheus-dev/plume-language",
    "stargazers_count": 2,
    "open_issues_count": 0,
    "forks_count": 0
  },
  {
    "full_name": "Delioos/crypto-curious-crusaders",
    "stargazers_count": 1,
    "open_issues_count": 0,
    "forks_count": 0
  },
  {
    "full_name": "gitbutlerapp/gitbutler",
    "stargazers_count": 9235,
    "open_issues_count": 210,
    "forks_count": 375
  },
  {
    "full_name": "lukeed/clsx",
    "stargazers_count": 7109,
    "open_issues_count": 5,
    "forks_count": 123
  },
  {
    "full_name": "zed-industries/zed",
    "stargazers_count": 28735,
    "open_issues_count": 1547,
    "forks_count": 1197
  },
  {
    "full_name": "dotnet/reactive",
    "stargazers_count": 6418,
    "open_issues_count": 157,
    "forks_count": 719
  },
  {
    "full_name": "floriankyn/MindToy-Discord-Bot",
    "stargazers_count": 4,
    "open_issues_count": 0,
    "forks_count": 0
  },
  {
    "full_name": "microsoft/reverse-proxy",
    "stargazers_count": 7710,
    "open_issues_count": 159,
    "forks_count": 761
  },
  {
    "full_name": "asc-lab/dotnetcore-microservices-poc",
    "stargazers_count": 1838,
    "open_issues_count": 5,
    "forks_count": 671
  },
  {
    "full_name": "charmbracelet/bubbletea",
    "stargazers_count": 23156,
    "open_issues_count": 87,
    "forks_count": 683
  },
  {
    "full_name": "expo/expo",
    "stargazers_count": 28164,
    "open_issues_count": 680,
    "forks_count": 4537
  },
  {
    "full_name": "sst/sst",
    "stargazers_count": 19590,
    "open_issues_count": 783,
    "forks_count": 1566
  },
  {
    "full_name": "joeferner/redis-commander",
    "stargazers_count": 3488,
    "open_issues_count": 51,
    "forks_count": 451
  },
  {
    "full_name": "nuxt/nuxt",
    "stargazers_count": 51081,
    "open_issues_count": 1009,
    "forks_count": 4675
  },
  {
    "full_name": "abi/screenshot-to-code",
    "stargazers_count": 45205,
    "open_issues_count": 77,
    "forks_count": 5310
  },
  {
    "full_name": "biomejs/biome",
    "stargazers_count": 9326,
    "open_issues_count": 114,
    "forks_count": 301
  },
  {
    "full_name": "dotnet/aspire-samples",
    "stargazers_count": 354,
    "open_issues_count": 54,
    "forks_count": 88
  },
  {
    "full_name": "dotnet/aspire",
    "stargazers_count": 2611,
    "open_issues_count": 430,
    "forks_count": 231
  },
  {
    "full_name": "dragonflydb/dragonfly",
    "stargazers_count": 22472,
    "open_issues_count": 137,
    "forks_count": 822
  },
  {
    "full_name": "analogjs/analog",
    "stargazers_count": 2046,
    "open_issues_count": 64,
    "forks_count": 184
  },
  {
    "full_name": "JasperFx/wolverine",
    "stargazers_count": 1042,
    "open_issues_count": 86,
    "forks_count": 109
  },
  {
    "full_name": "oskardudycz/EventSourcing.NetCore",
    "stargazers_count": 3203,
    "open_issues_count": 24,
    "forks_count": 494
  },
  {
    "full_name": "angular/angular",
    "stargazers_count": 94119,
    "open_issues_count": 1591,
    "forks_count": 24505
  },
  {
    "full_name": "nicolargo/glances",
    "stargazers_count": 24606,
    "open_issues_count": 241,
    "forks_count": 1433
  },
  {
    "full_name": "quarkusio/quarkus",
    "stargazers_count": 12943,
    "open_issues_count": 2519,
    "forks_count": 2452
  },
  {
    "full_name": "react-hook-form/react-hook-form",
    "stargazers_count": 39112,
    "open_issues_count": 22,
    "forks_count": 1953
  },
  {
    "full_name": "t3dotgg/server-actions-trpc-examples",
    "stargazers_count": 106,
    "open_issues_count": 3,
    "forks_count": 14
  },
  {
    "full_name": "openstatusHQ/openstatus",
    "stargazers_count": 3816,
    "open_issues_count": 52,
    "forks_count": 196
  },
  {
    "full_name": "FastEndpoints/FastEndpoints",
    "stargazers_count": 3736,
    "open_issues_count": 7,
    "forks_count": 237
  },
  {
    "full_name": "buresdv/Cork",
    "stargazers_count": 1519,
    "open_issues_count": 41,
    "forks_count": 78
  }
]