[
  {
    "full_name": "siglens/siglens",
    "stargazers_count": 1194,
    "open_issues_count": 110,
    "forks_count": 194
  },
  {
    "full_name": "LukeMathWalker/pavex",
    "stargazers_count": 1708,
    "open_issues_count": 5,
    "forks_count": 55
  },
  {
    "full_name": "plume-lang/plume",
    "stargazers_count": 10,
    "open_issues_count": 6,
    "forks_count": 2
  },
  {
    "full_name": "Delioos/crypto-curious-crusaders",
    "stargazers_count": 1,
    "open_issues_count": 0,
    "forks_count": 0
  },
  {
    "full_name": "gitbutlerapp/gitbutler",
    "stargazers_count": 12354,
    "open_issues_count": 264,
    "forks_count": 483
  },
  {
    "full_name": "lukeed/clsx",
    "stargazers_count": 8078,
    "open_issues_count": 11,
    "forks_count": 141
  },
  {
    "full_name": "zed-industries/zed",
    "stargazers_count": 46469,
    "open_issues_count": 2896,
    "forks_count": 2627
  },
  {
    "full_name": "dotnet/reactive",
    "stargazers_count": 6659,
    "open_issues_count": 170,
    "forks_count": 745
  },
  {
    "full_name": "floriankyn/MindToy-Discord-Bot",
    "stargazers_count": 5,
    "open_issues_count": 0,
    "forks_count": 1
  },
  {
    "full_name": "microsoft/reverse-proxy",
    "stargazers_count": 8422,
    "open_issues_count": 163,
    "forks_count": 828
  },
  {
    "full_name": "asc-lab/dotnetcore-microservices-poc",
    "stargazers_count": 1887,
    "open_issues_count": 5,
    "forks_count": 678
  },
  {
    "full_name": "charmbracelet/bubbletea",
    "stargazers_count": 26564,
    "open_issues_count": 112,
    "forks_count": 767
  },
  {
    "full_name": "expo/expo",
    "stargazers_count": 32551,
    "open_issues_count": 668,
    "forks_count": 5170
  },
  {
    "full_name": "sst/sst",
    "stargazers_count": 21342,
    "open_issues_count": 837,
    "forks_count": 1627
  },
  {
    "full_name": "joeferner/redis-commander",
    "stargazers_count": 3584,
    "open_issues_count": 54,
    "forks_count": 466
  },
  {
    "full_name": "nuxt/nuxt",
    "stargazers_count": 53969,
    "open_issues_count": 801,
    "forks_count": 4939
  },
  {
    "full_name": "abi/screenshot-to-code",
    "stargazers_count": 55956,
    "open_issues_count": 66,
    "forks_count": 6848
  },
  {
    "full_name": "biomejs/biome",
    "stargazers_count": 13902,
    "open_issues_count": 157,
    "forks_count": 420
  },
  {
    "full_name": "dotnet/aspire-samples",
    "stargazers_count": 615,
    "open_issues_count": 89,
    "forks_count": 178
  },
  {
    "full_name": "dotnet/aspire",
    "stargazers_count": 3602,
    "open_issues_count": 830,
    "forks_count": 397
  },
  {
    "full_name": "dragonflydb/dragonfly",
    "stargazers_count": 25213,
    "open_issues_count": 160,
    "forks_count": 908
  },
  {
    "full_name": "analogjs/analog",
    "stargazers_count": 2493,
    "open_issues_count": 21,
    "forks_count": 235
  },
  {
    "full_name": "JasperFx/wolverine",
    "stargazers_count": 1209,
    "open_issues_count": 71,
    "forks_count": 131
  },
  {
    "full_name": "oskardudycz/EventSourcing.NetCore",
    "stargazers_count": 3356,
    "open_issues_count": 21,
    "forks_count": 510
  },
  {
    "full_name": "angular/angular",
    "stargazers_count": 95643,
    "open_issues_count": 1623,
    "forks_count": 25184
  },
  {
    "full_name": "nicolargo/glances",
    "stargazers_count": 26234,
    "open_issues_count": 197,
    "forks_count": 1489
  },
  {
    "full_name": "quarkusio/quarkus",
    "stargazers_count": 13525,
    "open_issues_count": 2721,
    "forks_count": 2606
  },
  {
    "full_name": "react-hook-form/react-hook-form",
    "stargazers_count": 40979,
    "open_issues_count": 52,
    "forks_count": 2047
  },
  {
    "full_name": "t3dotgg/server-actions-trpc-examples",
    "stargazers_count": 117,
    "open_issues_count": 2,
    "forks_count": 14
  },
  {
    "full_name": "openstatusHQ/openstatus",
    "stargazers_count": 5986,
    "open_issues_count": 65,
    "forks_count": 375
  }
]